MailService/__init__.py
MailService/__main__.py
MailService/api.py
MailService/apy_test.py
MailService/const.py
MailService/service.py
pih_mail-1.24.dist-info/METADATA
pih_mail-1.24.dist-info/WHEEL
pih_mail-1.24.dist-info/entry_points.txt
pih_mail-1.24.dist-info/top_level.txt
pih_mail-1.24.dist-info/RECORD
