Metadata-Version: 2.1
Name: pih-mail
Version: 1.24
Summary: PIH Mail service package
Home-page: https://pacifichosp.com/
Author: Nikita Karachentsev
Author-email: it@pacifichosp.com
License: MIT
Requires-Dist: ipih
Requires-Dist: py3-validate-email
Requires-Dist: imap-tools
